<?xml version='1.0' encoding='UTF-8'?>
<song xmlns="http://openlyrics.info/namespace/2009/song" version="0.8" createdIn="OpenLP 2.4.6" modifiedIn="OpenLP 2.4.6" modifiedDate="2020-08-29T23:19:01">
  <properties>
    <titles>
      <title>Incomparável</title>
      <title>Imcomparável</title>
    </titles>
    <authors>
      <author>Nívea Soares</author>
    </authors>
  </properties>
  <lyrics>
    <verse name="v1">
      <lines>Sangue derramado, <br/>graça revelada<br/>Em Cristo, Filho de Deus.</lines>
    </verse>
    <verse name="v2">
      <lines>Sou o Teu desejo,<br/> És o meu Amado<br/>Tenho fome e sede de Ti.</lines>
    </verse>
    <verse name="v3">
      <lines>Mergulhado em Seu doce amor<br/>Sou curado, transformado.</lines>
    </verse>
    <verse name="v4">
      <lines>Atraído pelo Teu Espírito<br/>Eu prossigo de glória em glória.</lines>
    </verse>
    <verse name="v5">
      <lines>Te amo, Deus Poderoso.<br/>Incomparável, Teu amor me satisfaz.</lines>
    </verse>
    <verse name="v6">
      <lines>Sangue derramado,<br/>graça revelada<br/>Em Cristo, Filho de Deus.</lines>
    </verse>
    <verse name="v7">
      <lines>Sou o Teu desejo,<br/> És o meu Amado<br/>Tenho fome e sede de Ti.</lines>
    </verse>
    <verse name="v8">
      <lines>Mergulhado em Seu doce amor<br/>Sou curado, transformado.</lines>
    </verse>
    <verse name="v9">
      <lines>Atraído pelo Teu Espírito<br/>Eu prossigo de glória em glória.</lines>
    </verse>
    <verse name="v10">
      <lines>Te amo, Deus Poderoso.<br/>Incomparável, <br/>Teu amor me satisfaz.(2x)</lines>
    </verse>
    <verse name="v11">
      <lines>A vida eterna é te conhecer<br/>Único Deus, Glorioso Deus.</lines>
    </verse>
    <verse name="v12">
      <lines>O meu anseio é te conhecer<br/>Único Deus, Glorioso Deus. </lines>
    </verse>
    <verse name="v13">
      <lines>A vida eterna é te conhecer<br/>Único Deus, Glorioso Deus.</lines>
    </verse>
    <verse name="v14">
      <lines>O meu anseio é te conhecer<br/>Único Deus, Glorioso Deus. </lines>
    </verse>
    <verse name="v15">
      <lines>Te amo, Deus Poderoso.<br/>Incomparável,<br/> Teu amor me satisfaz.(2x)</lines>
    </verse>
  </lyrics>
</song>
