<?xml version='1.0' encoding='UTF-8'?>
<song xmlns="http://openlyrics.info/namespace/2009/song" version="0.8" createdIn="OpenLP 2.4.6" modifiedIn="OpenLP 2.4.6" modifiedDate="2018-04-13T12:17:04">
  <properties>
    <titles>
      <title>Manancial</title>
      <title>29- Manancial</title>
    </titles>
    <authors>
      <author>Aline Barros</author>
    </authors>
  </properties>
  <lyrics>
    <verse name="v1">
      <lines>Manancial, fonte de vida<br/>De onde eu preciso e quero beber todos os dias</lines>
    </verse>
    <verse name="v2">
      <lines>Bem mais que um desejo, Tu és essencial<br/>Pra sustentar a minha vida Senhor Jesus</lines>
    </verse>
    <verse name="v3">
      <lines>Eu tenho sede de Ti<br/>Minh'alma anseia por Ti<br/>Só me satisfaço quando<br/>Estou junto aos Teus pés</lines>
    </verse>
    <verse name="v4">
      <lines>Eu tenho sede de Ti<br/>Minh'alma anseia por Ti<br/>Manancial, única fonte de vida Tu és</lines>
    </verse>
    <verse name="v5">
      <lines/>
    </verse>
    <verse name="v6">
      <lines>Manancial, fonte de vida<br/>De onde eu preciso e quero beber todos os dias</lines>
    </verse>
    <verse name="v7">
      <lines>Bem mais que um desejo, Tu és essencial<br/>Pra sustentar a minha vida Senhor Jesus</lines>
    </verse>
    <verse name="v8">
      <lines>Eu tenho sede de Ti<br/>Minh'alma anseia por Ti<br/>Só me satisfaço quando<br/>Estou junto aos Teus pés</lines>
    </verse>
    <verse name="v9">
      <lines>Eu tenho sede de Ti<br/>Minh'alma anseia por Ti<br/>Manancial, única fonte de vida Tu és</lines>
    </verse>
  </lyrics>
</song>
